hyperbolic/__init__.py
hyperbolic/util.py
hyperbolic/euclid/__init__.py
hyperbolic/euclid/arc.py
hyperbolic/euclid/circle.py
hyperbolic/euclid/ellipse.py
hyperbolic/euclid/ellipse_arc.py
hyperbolic/euclid/intersection.py
hyperbolic/euclid/line.py
hyperbolic/euclid/origin_line.py
hyperbolic/euclid3d/__init__.py
hyperbolic/euclid3d/projection.py
hyperbolic/euclid3d/util.py
hyperbolic/poincare/__init__.py
hyperbolic/poincare/circle.py
hyperbolic/poincare/horocycle.py
hyperbolic/poincare/hypercycle.py
hyperbolic/poincare/line.py
hyperbolic/poincare/point.py
hyperbolic/poincare/polygon.py
hyperbolic/poincare/transform.py
hyperbolic/poincare/util.py
hyperbolic/tiles/__init__.py
hyperbolic/tiles/decorator.py
hyperbolic/tiles/edge.py
hyperbolic/tiles/tile.py
hyperbolic/tiles/tile_gen.py
hyperbolic/tiles/tile_layout.py
hyperbolic-2.0.0.dist-info/LICENSE.txt
hyperbolic-2.0.0.dist-info/METADATA
hyperbolic-2.0.0.dist-info/WHEEL
hyperbolic-2.0.0.dist-info/top_level.txt
hyperbolic-2.0.0.dist-info/RECORD
