Metadata-Version: 2.1
Name: hyperbolic
Version: 2.0.0
Summary: A Python 3 library for constructing and drawing hyperbolic geometry
Home-page: https://github.com/cduck/hyperbolic
Download-URL: https://github.com/cduck/hyperbolic/archive/2.0.0.tar.gz
Author: Casey Duckering
License: UNKNOWN
Keywords: hyperbolic,geometry,draw,SVG
Platform: UNKNOWN
Classifier: License :: OSI Approved :: MIT License
Classifier: Programming Language :: Python :: 3
Classifier: Framework :: IPython
Classifier: Framework :: Jupyter
License-File: LICENSE.txt
Requires-Dist: numpy
Requires-Dist: drawsvg (~=2.0)
